redisrpc/__init__.py
redisrpc/base.py
redisrpc/errors.py
redisrpc/version.py
redispubsub-0.0.7.dist-info/LICENSE
redispubsub-0.0.7.dist-info/METADATA
redispubsub-0.0.7.dist-info/WHEEL
redispubsub-0.0.7.dist-info/top_level.txt
redispubsub-0.0.7.dist-info/RECORD
