Metadata-Version: 2.1
Name: redispubsub
Version: 0.0.7
Summary: Redis RPC server for microservices
Home-page: https://github.com/munisisazade/redis-pub-sub
Author: Munis Isazade
Author-email: munisisazade@gmail.com
License: MIT
Platform: any
Classifier: Intended Audience :: Developers
Classifier: Programming Language :: Python
Classifier: Programming Language :: Python :: 3
Classifier: Programming Language :: Python :: 3.6
Classifier: Programming Language :: Python :: 3.7
Classifier: Programming Language :: Python :: 3.8
Classifier: Programming Language :: Python :: 3.9
Classifier: Programming Language :: Python :: 3.10
Classifier: Programming Language :: Python :: 3.11
Classifier: Programming Language :: Python :: 3.12
Classifier: License :: OSI Approved :: MIT License
Classifier: Operating System :: OS Independent
License-File: LICENSE
Requires-Dist: redis
Provides-Extra: redis
Requires-Dist: redis; extra == "redis"
